preditor/__init__.py
preditor/__main__.py
preditor/about_module.py
preditor/cli.py
preditor/config.py
preditor/constants.py
preditor/contexts.py
preditor/debug.py
preditor/enum.py
preditor/excepthooks.py
preditor/logging_config.py
preditor/osystem.py
preditor/plugins.py
preditor/prefs.py
preditor/settings.py
preditor/streamhandler_helper.py
preditor/version.py
preditor/weakref.py
preditor/cores/__init__.py
preditor/cores/core.py
preditor/dccs/.hab.json
preditor/dccs/maya/PrEditor_maya.mod
preditor/dccs/maya/README.md
preditor/dccs/maya/plug-ins/PrEditor_maya.py
preditor/dccs/studiomax/PackageContents.xml
preditor/dccs/studiomax/PrEditor-PrEditor_Show.mcr
preditor/dccs/studiomax/README.md
preditor/dccs/studiomax/preditor.ms
preditor/dccs/studiomax/preditor_menu.mnx
preditor/delayable_engine/__init__.py
preditor/delayable_engine/delayables.py
preditor/gui/__init__.py
preditor/gui/app.py
preditor/gui/codehighlighter.py
preditor/gui/completer.py
preditor/gui/console.py
preditor/gui/console_base.py
preditor/gui/dialog.py
preditor/gui/drag_tab_bar.py
preditor/gui/editor_chooser.py
preditor/gui/errordialog.py
preditor/gui/find_files.py
preditor/gui/level_buttons.py
preditor/gui/logger_window_handler.py
preditor/gui/logger_window_plugin.py
preditor/gui/loggerwindow.py
preditor/gui/newtabwidget.py
preditor/gui/output_console.py
preditor/gui/set_text_editor_path_dialog.py
preditor/gui/status_label.py
preditor/gui/suggest_path_quotes_dialog.py
preditor/gui/window.py
preditor/gui/workbox_mixin.py
preditor/gui/workbox_text_edit.py
preditor/gui/workboxwidget.py
preditor/gui/fuzzy_search/__init__.py
preditor/gui/fuzzy_search/fuzzy_search.py
preditor/gui/group_tab_widget/__init__.py
preditor/gui/group_tab_widget/group_tab_widget.py
preditor/gui/group_tab_widget/grouped_tab_menu.py
preditor/gui/group_tab_widget/grouped_tab_models.py
preditor/gui/group_tab_widget/grouped_tab_widget.py
preditor/gui/group_tab_widget/one_tab_widget.py
preditor/gui/qtdesigner/__init__.py
preditor-2.3.0.dist-info/licenses/LICENSE
preditor-2.3.0.dist-info/METADATA
preditor-2.3.0.dist-info/WHEEL
preditor-2.3.0.dist-info/entry_points.txt
preditor-2.3.0.dist-info/top_level.txt
preditor-2.3.0.dist-info/RECORD
