Metadata-Version: 2.4
Name: PrEditor
Version: 2.3.0
Summary: A python REPL and Editor and console based on Qt.
Author-email: Blur Studio <opensource@blur.com>
License: LGPL-3.0
Project-URL: Homepage, https://github.com/blurstudio/PrEditor
Project-URL: Source, https://github.com/blurstudio/PrEditor
Project-URL: Tracker, https://github.com/blurstudio/PrEditor/issues
Platform: any
Classifier: Development Status :: 5 - Production/Stable
Classifier: Intended Audience :: Developers
Classifier: Operating System :: OS Independent
Classifier: Programming Language :: Python
Classifier: Programming Language :: Python :: 3
Classifier: Programming Language :: Python :: Implementation :: CPython
Classifier: Programming Language :: Python :: Implementation :: PyPy
Requires-Python: >=3.7
License-File: LICENSE
Requires-Dist: charset-normalizer
Requires-Dist: importlib-metadata>=4.8.3
Requires-Dist: Qt.py>=1.4.4
Requires-Dist: signalslot>=0.1.2
Provides-Extra: cli
Requires-Dist: click>=7.1.2; extra == "cli"
Requires-Dist: click-default-group; extra == "cli"
Provides-Extra: dev
Requires-Dist: black; extra == "dev"
Requires-Dist: build; extra == "dev"
Requires-Dist: covdefaults; extra == "dev"
Requires-Dist: coverage; extra == "dev"
Requires-Dist: flake8; extra == "dev"
Requires-Dist: flake8-bugbear; extra == "dev"
Requires-Dist: Flake8-pyproject; extra == "dev"
Requires-Dist: pep8-naming; extra == "dev"
Requires-Dist: pytest; extra == "dev"
Requires-Dist: tox; extra == "dev"
Provides-Extra: qsci5
Requires-Dist: QScintilla; extra == "qsci5"
Provides-Extra: qsci6
Requires-Dist: PyQt6-QScintilla; extra == "qsci6"
Provides-Extra: shortcut
Requires-Dist: casement>=0.1.0; platform_system == "Windows" and extra == "shortcut"
Dynamic: license-file
